buf/validate/validate_pb2.py
buf/validate/validate_pb2.pyi
buf/validate/validate_pb2_grpc.py
com/terraquantum/default_value_pb2.py
com/terraquantum/default_value_pb2.pyi
com/terraquantum/default_value_pb2_grpc.py
com/terraquantum/authorization/v1alpha1/authorization_service_pb2.py
com/terraquantum/authorization/v1alpha1/authorization_service_pb2.pyi
com/terraquantum/authorization/v1alpha1/authorization_service_pb2_grpc.py
com/terraquantum/authorization/v1alpha1/check_authorization_pb2.py
com/terraquantum/authorization/v1alpha1/check_authorization_pb2.pyi
com/terraquantum/authorization/v1alpha1/check_authorization_pb2_grpc.py
com/terraquantum/authorization/v1alpha1/get_authorization_pb2.py
com/terraquantum/authorization/v1alpha1/get_authorization_pb2.pyi
com/terraquantum/authorization/v1alpha1/get_authorization_pb2_grpc.py
com/terraquantum/authorization/v1alpha1/set_authorization_pb2.py
com/terraquantum/authorization/v1alpha1/set_authorization_pb2.pyi
com/terraquantum/authorization/v1alpha1/set_authorization_pb2_grpc.py
com/terraquantum/channel/v1alpha1/channel_message_pb2.py
com/terraquantum/channel/v1alpha1/channel_message_pb2.pyi
com/terraquantum/channel/v1alpha1/channel_message_pb2_grpc.py
com/terraquantum/channel/v1alpha1/channel_service_pb2.py
com/terraquantum/channel/v1alpha1/channel_service_pb2.pyi
com/terraquantum/channel/v1alpha1/channel_service_pb2_grpc.py
com/terraquantum/channel/v1alpha1/create_channel_pb2.py
com/terraquantum/channel/v1alpha1/create_channel_pb2.pyi
com/terraquantum/channel/v1alpha1/create_channel_pb2_grpc.py
com/terraquantum/common/v1/organization/organization_member_status_pb2.py
com/terraquantum/common/v1/organization/organization_member_status_pb2.pyi
com/terraquantum/common/v1/organization/organization_member_status_pb2_grpc.py
com/terraquantum/common/v1/organization/organization_user_status_pb2.py
com/terraquantum/common/v1/organization/organization_user_status_pb2.pyi
tq42_grpc_client-1.0.271.dist-info/METADATA
tq42_grpc_client-1.0.271.dist-info/WHEEL
tq42_grpc_client-1.0.271.dist-info/top_level.txt
tq42_grpc_client-1.0.271.dist-info/RECORD
